Workbook
Name Slicer_Category: #N/A
Name Slicer_StoreLocation: #N/A

Sheet Customers
A1: CustomerID | B1: FirstName | C1: LastName | D1: Gender | E1: BirthDate | F1: City | G1: JoinDate
A2: C001 | B2: Michael | C2: Davis | D2: M | E2: 35319 | F2: Osborneport | G2: 44829
A3: C002 | B3: Michael | C3: Miller | D3: M | E3: 21780 | F3: New Gabrielleport | G3: 44138
A4: C003 | B4: Carol | C4: Hays | D4: F | E4: 38461 | F4: Port Allen | G4: 45334
A5: C004 | B5: Joseph | C5: Ward | D5: M | E5: 33771 | F5: East Edgarborough | G5: 45544
A6: C005 | B6: Jamie | C6: Salinas | D6: M | E6: 33773 | F6: Port Kimberly | G6: 44616
A7: C006 | B7: Danny | C7: Moore | D7: M | E7: 31688 | F7: Costaberg | G7: 44751
A8: C007 | B8: Erin | C8: Walker | D8: M | E8: 31058 | F8: West Jasmine | G8: 44482
A9: C008 | B9: Isaiah | C9: Williams | D9: M | E9: 22233 | F9: New Michaelland | G9: 45720
A10: C009 | B10: Richard | C10: Pacheco | D10: F | E10: 38214 | F10: West Lisaville | G10: 45764
A11: C010 | B11: Catherine | C11: Rice | D11: M | E11: 28106 | F11: West Carol | G11: 45861
A12: C011 | B12: Haley | C12: Williams | D12: M | E12: 35492 | F12: Leburgh | G12: 45058
A13: C012 | B13: Dale | C13: Perry | D13: M | E13: 32850 | F13: Lake Dawn | G13: 44393
... A201: C200 | B201: Ronald | C201: Haley | D201: M | E201: 37249 | F201: Jenniferbury | G201: 45832

Sheet Products
A1: ProductID | B1: ProductName | C1: Category | D1: SubCategory | E1: UnitPrice | F1: CostPrice
A2: P001 | B2: Like Camera | C2: Electronics | D2: Camera | E2: 1673.69 | F2: 1323.38
A3: P002 | B3: Audience Television | C3: Electronics | D3: Television | E3: 818.76 | F3: 527.62
A4: P003 | B4: Here Footwear | C4: Fashion | D4: Footwear | E4: 337.63 | F4: 169.03
A5: P004 | B5: Four Accessories | C5: Fashion | D5: Accessories | E5: 1853.77 | F5: 1363.52
A6: P005 | B6: Knowledge Bags | C6: Fashion | D6: Bags | E6: 1396.22 | F6: 1004.09
A7: P006 | B7: Company Fruits | C7: Groceries | D7: Fruits | E7: 318.05 | F7: 187.34
A8: P007 | B8: Understand Camera | C8: Electronics | D8: Camera | E8: 1474.12 | F8: 764.02
A9: P008 | B9: Recognize Footwear | C9: Fashion | D9: Footwear | E9: 109.78 | F9: 70.59
A10: P009 | B10: Us Snacks | C10: Groceries | D10: Snacks | E10: 123.19 | F10: 80.36
A11: P010 | B11: Step Smartphone | C11: Electronics | D11: Smartphone | E11: 1194.12 | F11: 838.95
A12: P011 | B12: Either Headphones | C12: Electronics | D12: Headphones | E12: 248.57 | F12: 190.67
A13: P012 | B13: Above Camera | C13: Electronics | D13: Camera | E13: 1193.09 | F13: 818.24
... A51: P050 | B51: Maybe Footwear | C51: Fashion | D51: Footwear | E51: 1044.64 | F51: 775.07

Sheet Stores
A1: StoreID | B1: StoreName | C1: City | D1: Region
A2: S001 | B2: MegaMart Jimenezborough | C2: Jimenezborough | D2: South
A3: S002 | B3: MegaMart Peckmouth | C3: Peckmouth | D3: East
A4: S003 | B4: MegaMart New Michele | C4: New Michele | D4: West
A5: S004 | B5: MegaMart Brianahaven | C5: Brianahaven | D5: North
A6: S005 | B6: MegaMart Johnmouth | C6: Johnmouth | D6: East

Sheet Sheet1
A3: Row Labels | B3: Sum of Total Sales
A4: Electronics | B4: 6316917.3
A5: Fashion | B5: 6232279.7
A6: Groceries | B6: 1752706.1
A7: Grand Total | B7: 14301903

Sheet Sheet2
A3: Row Labels | B3: Sum of Total Sales
A4: MegaMart New Michele | B4: 2920406.9
A5: MegaMart Brianahaven | B5: 2900701.1
A6: MegaMart Jimenezborough | B6: 2880114.7
A7: MegaMart Johnmouth | B7: 2847047.8
A8: MegaMart Peckmouth | B8: 2753632.6
A9: Grand Total | B9: 14301903

Sheet Sheet3
A3: Row Labels | B3: Sum of Total Sales
A4: Cash | B4: 3676072.9
A5: Credit Card | B5: 3673746.8
A6: Mobile Money | B6: 3558433.5
A7: Bank Transfer | B7: 3393650
A8: Grand Total | B8: 14301903

Sheet Sheet4
A3: Row Labels | B3: Sum of Total Sales
A4: Four Accessories | B4: 471228.33
A5: Present Television | B5: 477913.42
A6: Road Clothing | B6: 479596.9
A7: Like Camera | B7: 482608.51
A8: Piece Headphones | B8: 497149.73
A9: Beat Accessories | B9: 498224.74
A10: Traditional Laptop | B10: 521031.01
A11: Set Dairy | B11: 573777.08
A12: And Footwear | B12: 585613.02
A13: Book Television | B13: 605028.6
A14: Grand Total | B14: 5192171.3

Sheet Transactions
A1: TransactionID | B1: Date | C1: CustomerID | D1: ProductID | E1: StoreID | F1: Quantity | G1: Discount | H1: PaymentMethod | I1: Customer Name | J1: Product name | K1: Category | L1: StoreLocation | M1: Unit Price | N1: Total Sales
A2: T00001 | B2: 45461 | C2: C160 | D2: P014 | E2: S003 | F2: 1 | G2: 0.1 | H2: Bank Transfer | I2: =VLOOKUP(C2,Customers!A:C,2,FALSE)&" "&VLOOKUP(C2,Customers!A:C,3,FALSE) -> Meagan Macdonald | J2: =VLOOKUP(D2,Products!A:C,2,FALSE) -> Add Clothing | K2: =VLOOKUP(D2,Products!A:C,3,FALSE) -> Fashion | L2: =VLOOKUP(E2,Stores!A:B,2,FALSE) -> MegaMart New Michele | M2: =VLOOKUP(D2,Products!A:E,5,FALSE) -> 1342.75 | N2: =F2*M2*(1-G2) -> 1208.475
A3: T00002 | B3: 45232 | C3: C171 | D3: P030 | E3: S004 | F3: 3 | G3: 0.15 | H3: Bank Transfer | I3: =VLOOKUP(C3,Customers!A:C,2,FALSE)&" "&VLOOKUP(C3,Customers!A:C,3,FALSE) -> Christina Dominguez | J3: =VLOOKUP(D3,Products!A:C,2,FALSE) -> National Watches | K3: =VLOOKUP(D3,Products!A:C,3,FALSE) -> Fashion | L3: =VLOOKUP(E3,Stores!A:B,2,FALSE) -> MegaMart Brianahaven | M3: =VLOOKUP(D3,Products!A:E,5,FALSE) -> 29.24 | N3: =F3*M3*(1-G3) -> 74.562
A4: T00003 | B4: 45379 | C4: C142 | D4: P002 | E4: S002 | F4: 2 | G4: 0.15 | H4: Mobile Money | I4: =VLOOKUP(C4,Customers!A:C,2,FALSE)&" "&VLOOKUP(C4,Customers!A:C,3,FALSE) -> Suzanne Fox | J4: =VLOOKUP(D4,Products!A:C,2,FALSE) -> Audience Television | K4: =VLOOKUP(D4,Products!A:C,3,FALSE) -> Electronics | L4: =VLOOKUP(E4,Stores!A:B,2,FALSE) -> MegaMart Peckmouth | M4: =VLOOKUP(D4,Products!A:E,5,FALSE) -> 818.76 | N4: =F4*M4*(1-G4) -> 1391.892
A5: T00004 | B5: 45458 | C5: C174 | D5: P050 | E5: S002 | F5: 5 | G5: 0.1 | H5: Mobile Money | I5: =VLOOKUP(C5,Customers!A:C,2,FALSE)&" "&VLOOKUP(C5,Customers!A:C,3,FALSE) -> Scott Howell | J5: =VLOOKUP(D5,Products!A:C,2,FALSE) -> Maybe Footwear | K5: =VLOOKUP(D5,Products!A:C,3,FALSE) -> Fashion | L5: =VLOOKUP(E5,Stores!A:B,2,FALSE) -> MegaMart Peckmouth | M5: =VLOOKUP(D5,Products!A:E,5,FALSE) -> 1044.64 | N5: =F5*M5*(1-G5) -> 4700.88
A6: T00005 | B6: 45533 | C6: C141 | D6: P036 | E6: S001 | F6: 3 | G6: 0.1 | H6: Credit Card | I6: =VLOOKUP(C6,Customers!A:C,2,FALSE)&" "&VLOOKUP(C6,Customers!A:C,3,FALSE) -> Adam Lucas | J6: =VLOOKUP(D6,Products!A:C,2,FALSE) -> New Watches | K6: =VLOOKUP(D6,Products!A:C,3,FALSE) -> Fashion | L6: =VLOOKUP(E6,Stores!A:B,2,FALSE) -> MegaMart Jimenezborough | M6: =VLOOKUP(D6,Products!A:E,5,FALSE) -> 1501.46 | N6: =F6*M6*(1-G6) -> 4053.942
A7: T00006 | B7: 45744 | C7: C111 | D7: P036 | E7: S005 | F7: 5 | G7: 0.1 | H7: Mobile Money | I7: =VLOOKUP(C7,Customers!A:C,2,FALSE)&" "&VLOOKUP(C7,Customers!A:C,3,FALSE) -> Dylan Booker | J7: =VLOOKUP(D7,Products!A:C,2,FALSE) -> New Watches | K7: =VLOOKUP(D7,Products!A:C,3,FALSE) -> Fashion | L7: =VLOOKUP(E7,Stores!A:B,2,FALSE) -> MegaMart Johnmouth | M7: =VLOOKUP(D7,Products!A:E,5,FALSE) -> 1501.46 | N7: =F7*M7*(1-G7) -> 6756.57
A8: T00007 | B8: 45605 | C8: C114 | D8: P009 | E8: S004 | F8: 2 | G8: 0.15 | H8: Credit Card | I8: =VLOOKUP(C8,Customers!A:C,2,FALSE)&" "&VLOOKUP(C8,Customers!A:C,3,FALSE) -> Miranda Rodriguez | J8: =VLOOKUP(D8,Products!A:C,2,FALSE) -> Us Snacks | K8: =VLOOKUP(D8,Products!A:C,3,FALSE) -> Groceries | L8: =VLOOKUP(E8,Stores!A:B,2,FALSE) -> MegaMart Brianahaven | M8: =VLOOKUP(D8,Products!A:E,5,FALSE) -> 123.19 | N8: =F8*M8*(1-G8) -> 209.423
A9: T00008 | B9: 45440 | C9: C169 | D9: P005 | E9: S001 | F9: 3 | G9: 0.1 | H9: Cash | I9: =VLOOKUP(C9,Customers!A:C,2,FALSE)&" "&VLOOKUP(C9,Customers!A:C,3,FALSE) -> Travis Watson | J9: =VLOOKUP(D9,Products!A:C,2,FALSE) -> Knowledge Bags | K9: =VLOOKUP(D9,Products!A:C,3,FALSE) -> Fashion | L9: =VLOOKUP(E9,Stores!A:B,2,FALSE) -> MegaMart Jimenezborough | M9: =VLOOKUP(D9,Products!A:E,5,FALSE) -> 1396.22 | N9: =F9*M9*(1-G9) -> 3769.794
A10: T00009 | B10: 45539 | C10: C193 | D10: P035 | E10: S002 | F10: 3 | G10: 0.05 | H10: Credit Card | I10: =VLOOKUP(C10,Customers!A:C,2,FALSE)&" "&VLOOKUP(C10,Customers!A:C,3,FALSE) -> Donald Meza | J10: =VLOOKUP(D10,Products!A:C,2,FALSE) -> Chair Laptop | K10: =VLOOKUP(D10,Products!A:C,3,FALSE) -> Electronics | L10: =VLOOKUP(E10,Stores!A:B,2,FALSE) -> MegaMart Peckmouth | M10: =VLOOKUP(D10,Products!A:E,5,FALSE) -> 1562.43 | N10: =F10*M10*(1-G10) -> 4452.9255
A11: T00010 | B11: 45459 | C11: C038 | D11: P045 | E11: S001 | F11: 1 | G11: 0.05 | H11: Mobile Money | I11: =VLOOKUP(C11,Customers!A:C,2,FALSE)&" "&VLOOKUP(C11,Customers!A:C,3,FALSE) -> Tracey Davis | J11: =VLOOKUP(D11,Products!A:C,2,FALSE) -> Set Dairy | K11: =VLOOKUP(D11,Products!A:C,3,FALSE) -> Groceries | L11: =VLOOKUP(E11,Stores!A:B,2,FALSE) -> MegaMart Jimenezborough | M11: =VLOOKUP(D11,Products!A:E,5,FALSE) -> 1879.08 | N11: =F11*M11*(1-G11) -> 1785.126
A12: T00011 | B12: 45725 | C12: C157 | D12: P022 | E12: S001 | F12: 4 | G12: 0.15 | H12: Credit Card | I12: =VLOOKUP(C12,Customers!A:C,2,FALSE)&" "&VLOOKUP(C12,Customers!A:C,3,FALSE) -> Connie Terry | J12: =VLOOKUP(D12,Products!A:C,2,FALSE) -> How Vegetables | K12: =VLOOKUP(D12,Products!A:C,3,FALSE) -> Groceries | L12: =VLOOKUP(E12,Stores!A:B,2,FALSE) -> MegaMart Jimenezborough | M12: =VLOOKUP(D12,Products!A:E,5,FALSE) -> 25.57 | N12: =F12*M12*(1-G12) -> 86.938
A13: T00012 | B13: 45449 | C13: C184 | D13: P042 | E13: S004 | F13: 4 | G13: 0.15 | H13: Credit Card | I13: =VLOOKUP(C13,Customers!A:C,2,FALSE)&" "&VLOOKUP(C13,Customers!A:C,3,FALSE) -> Daniel Mcintyre | J13: =VLOOKUP(D13,Products!A:C,2,FALSE) -> Maybe Clothing | K13: =VLOOKUP(D13,Products!A:C,3,FALSE) -> Fashion | L13: =VLOOKUP(E13,Stores!A:B,2,FALSE) -> MegaMart Brianahaven | M13: =VLOOKUP(D13,Products!A:E,5,FALSE) -> 453.62 | N13: =F13*M13*(1-G13) -> 1542.308
... A5001: T05000 | B5001: 45489 | C5001: C053 | D5001: P034 | E5001: S004 | F5001: 5 | G5001: 0.15 | H5001: Cash | I5001: =VLOOKUP(C5001,Customers!A:C,2,FALSE)&" "&VLOOKUP(C5001,Customers!A:C,3,FALSE) -> Felicia Morgan | J5001: =VLOOKUP(D5001,Products!A:C,2,FALSE) -> Everything Laptop | K5001: =VLOOKUP(D5001,Products!A:C,3,FALSE) -> Electronics | L5001: =VLOOKUP(E5001,Stores!A:B,2,FALSE) -> MegaMart Brianahaven | M5001: =VLOOKUP(D5001,Products!A:E,5,FALSE) -> 428.05 | N5001: =F5001*M5001*(1-G5001) -> 1819.2125

Sheet Dashboard
